{
  "groupId" : "com.aspose",
  "artifactId" : "aspose-html",
  "id" : "25-2-1",
  "packageFiles" : [ {
    "size" : "2 MB",
    "name" : "aspose-html-25.2.1-javadoc.jar",
    "classifier" : "javadoc"
  }, {
    "size" : "32 MB",
    "name" : "aspose-html-25.2.1-jdk1.8.jar",
    "classifier" : "jdk1.8"
  }, {
    "size" : "32 MB",
    "name" : "aspose-html-25.2.1-jdk11.jar",
    "classifier" : "jdk11"
  }, {
    "size" : "32 MB",
    "name" : "aspose-html-25.2.1-jdk17.jar",
    "classifier" : "jdk17"
  }, {
    "size" : "32 MB",
    "name" : "aspose-html-25.2.1-jdk21.jar",
    "classifier" : "jdk21"
  }, {
    "size" : "32 MB",
    "name" : "aspose-html-25.2.1-jdk8.jar",
    "classifier" : "jdk8"
  }, {
    "size" : "32 MB",
    "name" : "aspose-html-25.2.1.jar"
  }, {
    "size" : "425 bytes",
    "name" : "aspose-html-25.2.1.pom"
  }, {
    "size" : "172 MB",
    "name" : "aspose-html-25.2.1.zip"
  } ],
  "releasehDate" : "2025-02-13T09:09:41+00:00",
  "version" : "25.2.1",
  "ReleaseNotes" : "https://releases.aspose.com/html/java/release-notes/2025/aspose-html-for-java-25-2-1-release-notes/"
}