{
  "groupId" : "com.aspose",
  "classifier" : "jdk16",
  "artifactId" : "aspose-email",
  "id" : "21-1",
  "packageFiles" : [ {
    "size" : "6.51 MB",
    "name" : "aspose-email-21.1-android.via.java.jar",
    "classifier" : "android.via.java"
  }, {
    "size" : "4.37 MB",
    "name" : "aspose-email-21.1-javadoc.jar",
    "classifier" : "javadoc"
  }, {
    "size" : "12.56 MB",
    "name" : "aspose-email-21.1-jdk16.jar",
    "classifier" : "jdk16"
  }, {
    "size" : "1.72 KB",
    "name" : "aspose-email-21.1.pom"
  } ],
  "releasehDate" : "2021-02-01T00:00:00+00:00",
  "version" : "21.1",
  "ReleaseNotes" : "https://docs.aspose.com/email/java/aspose-email-for-java-21-1-release-notes/"
}