{
  "groupId" : "com.aspose",
  "classifier" : "jdk16",
  "artifactId" : "aspose-email",
  "id" : "23-8",
  "packageFiles" : [ {
    "size" : "4 MB",
    "name" : "aspose-email-23.8-javadoc.jar",
    "classifier" : "javadoc"
  }, {
    "size" : "13 MB",
    "name" : "aspose-email-23.8-jdk16.jar",
    "classifier" : "jdk16"
  }, {
    "size" : "1 KB",
    "name" : "aspose-email-23.8.pom"
  } ],
  "releasehDate" : "2023-09-21T19:07:13+00:00",
  "version" : "23.8",
  "ReleaseNotes" : "https://releases.aspose.com/email/java/release-notes/2023/aspose-email-for-java-23-8-release-notes/"
}