{
  "groupId" : "com.aspose",
  "classifier" : "jdk16",
  "artifactId" : "aspose-slides",
  "id" : "24-7",
  "packageFiles" : [ {
    "size" : "4 MB",
    "name" : "aspose-slides-24.7-android.via.java-javadoc.jar",
    "classifier" : "android.via.java-javadoc"
  }, {
    "size" : "30 MB",
    "name" : "aspose-slides-24.7-android.via.java.jar",
    "classifier" : "android.via.java"
  }, {
    "size" : "1 KB",
    "name" : "aspose-slides-24.7-android.via.java.pom"
  }, {
    "size" : "3 MB",
    "name" : "aspose-slides-24.7-javadoc.jar",
    "classifier" : "javadoc"
  }, {
    "size" : "29 MB",
    "name" : "aspose-slides-24.7-jdk16.jar",
    "classifier" : "jdk16"
  }, {
    "size" : "395 bytes",
    "name" : "aspose-slides-24.7.pom"
  } ],
  "releasehDate" : "2024-07-18T16:58:25+00:00",
  "version" : "24.7",
  "ReleaseNotes" : "https://releases.aspose.com/slides/java/release-notes/2024/aspose-slides-for-java-24-7-release-notes/"
}