{
  "groupId" : "com.aspose",
  "artifactId" : "aspose-cells",
  "id" : "17-10",
  "packageFiles" : [ {
    "size" : "1.47 MB",
    "name" : "aspose-cells-17.10-javadoc.jar",
    "classifier" : "javadoc"
  }, {
    "size" : "6.41 MB",
    "name" : "aspose-cells-17.10.jar"
  }, {
    "size" : "454 bytes",
    "name" : "aspose-cells-17.10.pom"
  } ],
  "releasehDate" : "2017-10-20T00:00:00+00:00",
  "version" : "17.10",
  "ReleaseNotes" : "https://docs.aspose.com/cells/java/aspose-cells-for-java-17-10-release-notes/"
}