{
  "groupId" : "com.aspose",
  "classifier" : "jdk16",
  "artifactId" : "aspose-words",
  "id" : "17-2-0",
  "packageFiles" : [ {
    "size" : "2.17 MB",
    "name" : "aspose-words-17.2.0-javadoc.jar",
    "classifier" : "javadoc"
  }, {
    "size" : "10.96 MB",
    "name" : "aspose-words-17.2.0-jdk16.jar",
    "classifier" : "jdk16"
  }, {
    "size" : "455 bytes",
    "name" : "aspose-words-17.2.0.pom"
  } ],
  "releasehDate" : "2017-02-08T00:00:00+00:00",
  "version" : "17.2.0",
  "ReleaseNotes" : "https://releases.aspose.com/words/java/release-notes/2017/aspose-words-for-java-17-2-0-release-notes/"
}