{
  "groupId" : "com.aspose",
  "classifier" : "jdk16",
  "artifactId" : "aspose-diagram",
  "id" : "18-10",
  "packageFiles" : [ {
    "size" : "816.72 KB",
    "name" : "aspose-diagram-18.10-javadoc.jar",
    "classifier" : "javadoc"
  }, {
    "size" : "3.12 MB",
    "name" : "aspose-diagram-18.10-jdk16.jar",
    "classifier" : "jdk16"
  }, {
    "size" : "451 bytes",
    "name" : "aspose-diagram-18.10.pom"
  } ],
  "releasehDate" : "2018-10-18T00:00:00+00:00",
  "version" : "18.10",
  "ReleaseNotes" : "https://docs.aspose.com/diagram/java/aspose-diagram-for-java-18-10-release-notes/"
}