{
  "groupId" : "com.aspose",
  "artifactId" : "aspose-barcode",
  "id" : "20-1",
  "packageFiles" : [ {
    "size" : "423.71 KB",
    "name" : "aspose-barcode-20.1-android.via.java-javadoc.jar",
    "classifier" : "android.via.java-javadoc"
  }, {
    "size" : "6.78 MB",
    "name" : "aspose-barcode-20.1-android.via.java.jar",
    "classifier" : "android.via.java"
  }, {
    "size" : "448.65 KB",
    "name" : "aspose-barcode-20.1-control.android.via.java-javadoc.jar",
    "classifier" : "control.android.via.java-javadoc"
  }, {
    "size" : "6.00 MB",
    "name" : "aspose-barcode-20.1-control.android.via.java.aar",
    "classifier" : "control.android.via.java.aar"
  }, {
    "size" : "446.68 KB",
    "name" : "aspose-barcode-20.1-javadoc.jar",
    "classifier" : "javadoc"
  }, {
    "size" : "10.35 MB",
    "name" : "aspose-barcode-20.1-jdk17.jar",
    "classifier" : "jdk17"
  }, {
    "size" : "10.35 MB",
    "name" : "aspose-barcode-20.1.jar"
  }, {
    "size" : "452 bytes",
    "name" : "aspose-barcode-20.1.pom"
  } ],
  "releasehDate" : "2020-01-29T00:00:00+00:00",
  "version" : "20.1",
  "ReleaseNotes" : "https://docs.aspose.com/barcode/java/aspose-barcode-for-java-20-1-release-notes/"
}
