{
  "groupId" : "com.aspose",
  "artifactId" : "aspose-barcode",
  "id" : "7-7-0",
  "packageFiles" : [ {
    "size" : "279.25 KB",
    "name" : "aspose-barcode-7.7.0-javadoc.jar",
    "classifier" : "javadoc"
  }, {
    "size" : "6.11 MB",
    "name" : "aspose-barcode-7.7.0.jar"
  }, {
    "size" : "456 bytes",
    "name" : "aspose-barcode-7.7.0.pom"
  } ],
  "releasehDate" : "2016-03-11T00:00:00+00:00",
  "version" : "7.7.0",
  "ReleaseNotes" : "https://releases.aspose.com/barcode/java/release-notes/2016/aspose-barcode-for-java-7-7-0-release-notes/"
}
