{
  "groupId" : "com.aspose",
  "artifactId" : "aspose-cad",
  "id" : "22-6-1",
  "packageFiles" : [ {
    "size" : "15 MB",
    "name" : "aspose-cad-22.6.1-javadoc.jar",
    "classifier" : "javadoc"
  }, {
    "size" : "33 MB",
    "name" : "aspose-cad-22.6.1.jar"
  }, {
    "size" : "832 bytes",
    "name" : "aspose-cad-22.6.1.pom"
  } ],
  "releasehDate" : "2022-08-29T21:25:21+00:00",
  "version" : "22.6.1",
  "ReleaseNotes" : "https://releases.aspose.com/cad/java/release-notes/2022/aspose-cad-for-java-22-6-release-notes/"
}
